.coveragerc
CHANGES.rst
MANIFEST.in
README.rst
buildout.cfg
requirements.txt
setup.cfg
setup.py
Products/__init__.py
Products.MemcachedManager.egg-info/PKG-INFO
Products.MemcachedManager.egg-info/SOURCES.txt
Products.MemcachedManager.egg-info/dependency_links.txt
Products.MemcachedManager.egg-info/entry_points.txt
Products.MemcachedManager.egg-info/namespace_packages.txt
Products.MemcachedManager.egg-info/not-zip-safe
Products.MemcachedManager.egg-info/requires.txt
Products.MemcachedManager.egg-info/top_level.txt
Products/MemcachedManager/MemcachedManager.py
Products/MemcachedManager/__init__.py
Products/MemcachedManager/cache.gif
Products/MemcachedManager/dtml/addMM.dtml
Products/MemcachedManager/dtml/propsMM.dtml
Products/MemcachedManager/dtml/statsMM.dtml
Products/MemcachedManager/tests/__init__.py
Products/MemcachedManager/tests/mcmtc.py
Products/MemcachedManager/tests/memcache.py
Products/MemcachedManager/tests/testMemcacheStub.py
Products/MemcachedManager/tests/testMemcachedManager.py
Products/MemcachedManager/tests/testSetup.py
docs/LICENSE.ZPL