Metadata-Version: 2.1
Name: Products.MemcachedManager
Version: 1.1
Summary: Memcached cache manager for Zope.
Home-page: https://github.com/collective/Products.MemcachedManager
Author: Sidnei da Silva
Author-email: plone-developers@lists.sourceforge.net
License: UNKNOWN
Keywords: memcached Zope cache cachemanager
Platform: UNKNOWN
Classifier: Development Status :: 4 - Beta
Classifier: Environment :: Web Environment
Classifier: Framework :: Zope2
Classifier: Intended Audience :: Developers
Classifier: Intended Audience :: System Administrators
Classifier: License :: OSI Approved :: Zope Public License
Classifier: Operating System :: OS Independent
Classifier: Programming Language :: Python
Classifier: Programming Language :: Python :: 2
Classifier: Programming Language :: Python :: 2.7
Classifier: Programming Language :: Python :: 3
Classifier: Programming Language :: Python :: 3.6
Classifier: Programming Language :: Python :: 3.7
Classifier: Programming Language :: Python :: 3.8
Classifier: Topic :: Software Development :: Libraries :: Python Modules
Provides-Extra: pylibmc
Provides-Extra: python-memcached
